[{"id":1,"Name":"Pearle Cruess","Email Adress":"pcruess0@jigsy.com","Role":"Super Admin","Use Status":"Online"},
{"id":2,"Name":"Marice Brownell","Email Adress":"mbrownell1@redcross.org","Role":"Admin","Use Status":"Offline"},
{"id":3,"Name":"Hesther Mullin","Email Adress":"hmullin2@sbwire.com","Role":"Super Admin","Use Status":"Offline"},
{"id":4,"Name":"Susanna Beckley","Email Adress":"sbeckley3@naver.com","Role":"Super Admin","Use Status":"Offline"},
{"id":5,"Name":"Corrianne Shirland","Email Adress":"cshirland4@independent.co.uk","Role":"Super Admin","Use Status":"Online"},
{"id":6,"Name":"Moshe Babington","Email Adress":"mbabington5@irs.gov","Role":"Admin","Use Status":"Online"},
{"id":7,"Name":"Boigie Menezes","Email Adress":"bmenezes6@t-online.de","Role":"Super Admin","Use Status":"Offline"},
{"id":8,"Name":"Wang Agett","Email Adress":"wagett7@timesonline.co.uk","Role":"Admin","Use Status":"Offline"},
{"id":9,"Name":"Michele Sambrook","Email Adress":"msambrook8@accuweather.com","Role":"Admin","Use Status":"Online"},
{"id":10,"Name":"Gaspard Braidman","Email Adress":"gbraidman9@1688.com","Role":"Super Admin","Use Status":"Online"},
{"id":11,"Name":"Conant Wrinch","Email Adress":"cwrincha@cdc.gov","Role":"Admin","Use Status":"Online"},
{"id":12,"Name":"Stoddard Gladbach","Email Adress":"sgladbachb@bandcamp.com","Role":"Super Admin","Use Status":"Online"},
{"id":13,"Name":"Rhianon Erington","Email Adress":"reringtonc@dyndns.org","Role":"Admin","Use Status":"Online"},
{"id":14,"Name":"Karita Crimp","Email Adress":"kcrimpd@google.cn","Role":"Super Admin","Use Status":"Offline"},
{"id":15,"Name":"Ralf Petracci","Email Adress":"rpetraccie@sogou.com","Role":"Super Admin","Use Status":"Offline"},
{"id":16,"Name":"Gracie Thripp","Email Adress":"gthrippf@sakura.ne.jp","Role":"Super Admin","Use Status":"Online"},
{"id":17,"Name":"Darlene Bendson","Email Adress":"dbendsong@shinystat.com","Role":"Admin","Use Status":"Online"},
{"id":18,"Name":"Gipsy Pessolt","Email Adress":"gpessolth@surveymonkey.com","Role":"Super Admin","Use Status":"Online"},
{"id":19,"Name":"Christoforo Benny","Email Adress":"cbennyi@blogs.com","Role":"Admin","Use Status":"Offline"},
{"id":20,"Name":"Mirella Quaif","Email Adress":"mquaifj@skype.com","Role":"Super Admin","Use Status":"Online"},
{"id":21,"Name":"Xenia Grivori","Email Adress":"xgrivorik@jigsy.com","Role":"Admin","Use Status":"Offline"},
{"id":22,"Name":"Konstantin Stanners","Email Adress":"kstannersl@hud.gov","Role":"Super Admin","Use Status":"Offline"},
{"id":23,"Name":"Alon Jinkinson","Email Adress":"ajinkinsonm@feedburner.com","Role":"Super Admin","Use Status":"Offline"},
{"id":24,"Name":"Irv Biddulph","Email Adress":"ibiddulphn@topsy.com","Role":"Super Admin","Use Status":"Online"},
{"id":25,"Name":"Mei Heckner","Email Adress":"mhecknero@blog.com","Role":"Super Admin","Use Status":"Offline"},
{"id":26,"Name":"Pyotr Maryin","Email Adress":"pmaryinp@devhub.com","Role":"Admin","Use Status":"Offline"},
{"id":27,"Name":"Grove Laroux","Email Adress":"glarouxq@dedecms.com","Role":"Admin","Use Status":"Offline"},
{"id":28,"Name":"Elfrieda Tremain","Email Adress":"etremainr@zdnet.com","Role":"Admin","Use Status":"Online"},
{"id":29,"Name":"Leone Hannah","Email Adress":"lhannahs@vimeo.com","Role":"Super Admin","Use Status":"Online"},
{"id":30,"Name":"Marcellus Dudleston","Email Adress":"mdudlestont@liveinternet.ru","Role":"Super Admin","Use Status":"Online"},
{"id":31,"Name":"Hugibert Conduit","Email Adress":"hconduitu@163.com","Role":"Super Admin","Use Status":"Offline"},
{"id":32,"Name":"Ilario Thomesson","Email Adress":"ithomessonv@yahoo.com","Role":"Super Admin","Use Status":"Online"},
{"id":33,"Name":"Lily Adamczyk","Email Adress":"ladamczykw@prnewswire.com","Role":"Super Admin","Use Status":"Offline"},
{"id":34,"Name":"Son McMichael","Email Adress":"smcmichaelx@diigo.com","Role":"Super Admin","Use Status":"Online"},
{"id":35,"Name":"Giavani Cobbald","Email Adress":"gcobbaldy@stumbleupon.com","Role":"Super Admin","Use Status":"Offline"},
{"id":36,"Name":"Brigitte Riteley","Email Adress":"briteleyz@bravesites.com","Role":"Admin","Use Status":"Offline"},
{"id":37,"Name":"Gwenora Claige","Email Adress":"gclaige10@cmu.edu","Role":"Admin","Use Status":"Online"},
{"id":38,"Name":"Micky Temperton","Email Adress":"mtemperton11@utexas.edu","Role":"Super Admin","Use Status":"Online"},
{"id":39,"Name":"Torre Thonger","Email Adress":"tthonger12@disqus.com","Role":"Admin","Use Status":"Offline"},
{"id":40,"Name":"Perrine Oyley","Email Adress":"poyley13@godaddy.com","Role":"Super Admin","Use Status":"Offline"},
{"id":41,"Name":"Nicol Longlands","Email Adress":"nlonglands14@fotki.com","Role":"Admin","Use Status":"Offline"},
{"id":42,"Name":"Donnell Eakins","Email Adress":"deakins15@shinystat.com","Role":"Super Admin","Use Status":"Online"},
{"id":43,"Name":"Darcie Terrans","Email Adress":"dterrans16@domainmarket.com","Role":"Admin","Use Status":"Offline"},
{"id":44,"Name":"Dewey Keymar","Email Adress":"dkeymar17@hubpages.com","Role":"Super Admin","Use Status":"Online"},
{"id":45,"Name":"Galvin Brockington","Email Adress":"gbrockington18@icq.com","Role":"Admin","Use Status":"Online"},
{"id":46,"Name":"Court Dast","Email Adress":"cdast19@wikia.com","Role":"Admin","Use Status":"Online"},
{"id":47,"Name":"Ester Giacoppoli","Email Adress":"egiacoppoli1a@irs.gov","Role":"Super Admin","Use Status":"Offline"},
{"id":48,"Name":"Maggi Dell'Abbate","Email Adress":"mdellabbate1b@histats.com","Role":"Super Admin","Use Status":"Online"},
{"id":49,"Name":"Raymond Gandy","Email Adress":"rgandy1c@jimdo.com","Role":"Super Admin","Use Status":"Offline"},
{"id":50,"Name":"Norrie Goldman","Email Adress":"ngoldman1d@macromedia.com","Role":"Admin","Use Status":"Offline"},
{"id":51,"Name":"Simonette Daniaud","Email Adress":"sdaniaud1e@shutterfly.com","Role":"Admin","Use Status":"Offline"},
{"id":52,"Name":"Eleni Kubasek","Email Adress":"ekubasek1f@columbia.edu","Role":"Super Admin","Use Status":"Online"},
{"id":53,"Name":"Hasheem Haborn","Email Adress":"hhaborn1g@google.cn","Role":"Admin","Use Status":"Offline"},
{"id":54,"Name":"Audi Covolini","Email Adress":"acovolini1h@discovery.com","Role":"Admin","Use Status":"Online"},
{"id":55,"Name":"Colby Wrettum","Email Adress":"cwrettum1i@blogs.com","Role":"Super Admin","Use Status":"Online"},
{"id":56,"Name":"Alfie Gredden","Email Adress":"agredden1j@de.vu","Role":"Super Admin","Use Status":"Online"},
{"id":57,"Name":"Missie Hentzer","Email Adress":"mhentzer1k@senate.gov","Role":"Super Admin","Use Status":"Online"},
{"id":58,"Name":"Herta Loisi","Email Adress":"hloisi1l@joomla.org","Role":"Admin","Use Status":"Offline"},
{"id":59,"Name":"Saleem Jerrold","Email Adress":"sjerrold1m@dedecms.com","Role":"Super Admin","Use Status":"Online"},
{"id":60,"Name":"Hewet Ryal","Email Adress":"hryal1n@cbslocal.com","Role":"Admin","Use Status":"Online"},
{"id":61,"Name":"Natalie Inker","Email Adress":"ninker1o@virginia.edu","Role":"Super Admin","Use Status":"Online"},
{"id":62,"Name":"Karlan Gayle","Email Adress":"kgayle1p@amazonaws.com","Role":"Super Admin","Use Status":"Online"},
{"id":63,"Name":"Delinda Bingell","Email Adress":"dbingell1q@blogs.com","Role":"Admin","Use Status":"Offline"},
{"id":64,"Name":"Timmy Mardoll","Email Adress":"tmardoll1r@mozilla.com","Role":"Admin","Use Status":"Offline"},
{"id":65,"Name":"Joyce Rudledge","Email Adress":"jrudledge1s@nydailynews.com","Role":"Super Admin","Use Status":"Offline"},
{"id":66,"Name":"Henriette Matthew","Email Adress":"hmatthew1t@hao123.com","Role":"Super Admin","Use Status":"Offline"},
{"id":67,"Name":"Alvina Llop","Email Adress":"allop1u@loc.gov","Role":"Admin","Use Status":"Offline"},
{"id":68,"Name":"Dore Brasher","Email Adress":"dbrasher1v@simplemachines.org","Role":"Super Admin","Use Status":"Online"},
{"id":69,"Name":"Dorine Ransbury","Email Adress":"dransbury1w@github.com","Role":"Admin","Use Status":"Online"},
{"id":70,"Name":"Jaye Tuminini","Email Adress":"jtuminini1x@techcrunch.com","Role":"Super Admin","Use Status":"Offline"},
{"id":71,"Name":"Wylma Wyldish","Email Adress":"wwyldish1y@seattletimes.com","Role":"Super Admin","Use Status":"Online"},
{"id":72,"Name":"Stormy Warn","Email Adress":"swarn1z@bloglines.com","Role":"Super Admin","Use Status":"Online"},
{"id":73,"Name":"Loria Raeburn","Email Adress":"lraeburn20@liveinternet.ru","Role":"Super Admin","Use Status":"Offline"},
{"id":74,"Name":"Berny Gately","Email Adress":"bgately21@aol.com","Role":"Super Admin","Use Status":"Online"},
{"id":75,"Name":"Roze Chevalier","Email Adress":"rchevalier22@cocolog-nifty.com","Role":"Super Admin","Use Status":"Online"},
{"id":76,"Name":"Josh Krug","Email Adress":"jkrug23@examiner.com","Role":"Admin","Use Status":"Offline"},
{"id":77,"Name":"Robert Belhome","Email Adress":"rbelhome24@sina.com.cn","Role":"Super Admin","Use Status":"Online"},
{"id":78,"Name":"Kellen Talman","Email Adress":"ktalman25@comsenz.com","Role":"Super Admin","Use Status":"Online"},
{"id":79,"Name":"Tomi Veryan","Email Adress":"tveryan26@xrea.com","Role":"Super Admin","Use Status":"Offline"},
{"id":80,"Name":"Travis Monard","Email Adress":"tmonard27@java.com","Role":"Admin","Use Status":"Online"},
{"id":81,"Name":"Alisa Dearnaly","Email Adress":"adearnaly28@slashdot.org","Role":"Super Admin","Use Status":"Offline"},
{"id":82,"Name":"Dina D'Ambrosi","Email Adress":"ddambrosi29@xinhuanet.com","Role":"Super Admin","Use Status":"Offline"},
{"id":83,"Name":"Dar Younger","Email Adress":"dyounger2a@google.cn","Role":"Admin","Use Status":"Offline"},
{"id":84,"Name":"Sigismond Chene","Email Adress":"schene2b@ebay.co.uk","Role":"Admin","Use Status":"Offline"},
{"id":85,"Name":"Carita Lichtfoth","Email Adress":"clichtfoth2c@netlog.com","Role":"Admin","Use Status":"Online"},
{"id":86,"Name":"Blondy Angeli","Email Adress":"bangeli2d@vimeo.com","Role":"Admin","Use Status":"Offline"},
{"id":87,"Name":"Elinor Andriss","Email Adress":"eandriss2e@sourceforge.net","Role":"Admin","Use Status":"Offline"},
{"id":88,"Name":"Lydie Cross","Email Adress":"lcross2f@macromedia.com","Role":"Admin","Use Status":"Offline"},
{"id":89,"Name":"Jan Selbie","Email Adress":"jselbie2g@freewebs.com","Role":"Admin","Use Status":"Offline"},
{"id":90,"Name":"Kurtis Luxon","Email Adress":"kluxon2h@hc360.com","Role":"Super Admin","Use Status":"Offline"},
{"id":91,"Name":"Lari Tremontana","Email Adress":"ltremontana2i@storify.com","Role":"Super Admin","Use Status":"Online"},
{"id":92,"Name":"Clayson Littlejohn","Email Adress":"clittlejohn2j@wunderground.com","Role":"Admin","Use Status":"Online"},
{"id":93,"Name":"Melisenda Snead","Email Adress":"msnead2k@vinaora.com","Role":"Super Admin","Use Status":"Online"},
{"id":94,"Name":"Felipe Symington","Email Adress":"fsymington2l@wired.com","Role":"Admin","Use Status":"Offline"},
{"id":95,"Name":"Emelyne Roller","Email Adress":"eroller2m@wikispaces.com","Role":"Super Admin","Use Status":"Offline"},
{"id":96,"Name":"Eliza Dunkerley","Email Adress":"edunkerley2n@phpbb.com","Role":"Admin","Use Status":"Offline"},
{"id":97,"Name":"Levy Phillis","Email Adress":"lphillis2o@hibu.com","Role":"Super Admin","Use Status":"Offline"},
{"id":98,"Name":"Woodie Fordham","Email Adress":"wfordham2p@issuu.com","Role":"Admin","Use Status":"Offline"},
{"id":99,"Name":"Kathye Hards","Email Adress":"khards2q@huffingtonpost.com","Role":"Super Admin","Use Status":"Offline"},
{"id":100,"Name":"Bastien Lill","Email Adress":"blill2r@indiatimes.com","Role":"Super Admin","Use Status":"Online"}]